librus_terminal/__init__.py
librus_terminal/__main__.py
librus_terminal/authorization_commands.py
librus_terminal/command_parsing.py
librus_terminal/exceptions.py
librus_terminal/grades_commands.py
librus_terminal/help_command.py
librus_terminal/librus_session.py
librus_terminal/librus_terminal.py
librus_terminal/messages_commands.py
librus_terminal/other_commands.py
librus_terminal-0.1.1.dist-info/METADATA
librus_terminal-0.1.1.dist-info/WHEEL
librus_terminal-0.1.1.dist-info/entry_points.txt
librus_terminal-0.1.1.dist-info/top_level.txt
librus_terminal-0.1.1.dist-info/RECORD
